mazelib/__init__.py
mazelib/mazelib.py
mazelib/generate/AldousBroder.pxd
mazelib/generate/AldousBroder.py
mazelib/generate/BacktrackingGenerator.pxd
mazelib/generate/BacktrackingGenerator.py
mazelib/generate/BinaryTree.pxd
mazelib/generate/BinaryTree.py
mazelib/generate/CellularAutomaton.pxd
mazelib/generate/CellularAutomaton.py
mazelib/generate/Division.pxd
mazelib/generate/Division.py
mazelib/generate/DungeonRooms.pxd
mazelib/generate/DungeonRooms.py
mazelib/generate/Ellers.pxd
mazelib/generate/Ellers.py
mazelib/generate/GrowingTree.pxd
mazelib/generate/GrowingTree.py
mazelib/generate/HuntAndKill.pxd
mazelib/generate/HuntAndKill.py
mazelib/generate/Kruskal.pxd
mazelib/generate/Kruskal.py
mazelib/generate/MazeGenAlgo.pxd
mazelib/generate/MazeGenAlgo.py
mazelib/generate/Prims.pxd
mazelib/generate/Prims.py
mazelib/generate/Sidewinder.pxd
mazelib/generate/Sidewinder.py
mazelib/generate/TrivialMaze.pxd
mazelib/generate/TrivialMaze.py
mazelib/generate/Wilsons.pxd
mazelib/generate/Wilsons.py
mazelib/generate/__init__.py
mazelib/solve/BacktrackingSolver.pxd
mazelib/solve/BacktrackingSolver.py
mazelib/solve/Chain.pxd
mazelib/solve/Chain.py
mazelib/solve/Collision.pxd
mazelib/solve/Collision.py
mazelib/solve/MazeSolveAlgo.pxd
mazelib/solve/MazeSolveAlgo.py
mazelib/solve/RandomMouse.pxd
mazelib/solve/RandomMouse.py
mazelib/solve/ShortestPath.pxd
mazelib/solve/ShortestPath.py
mazelib/solve/ShortestPaths.pxd
mazelib/solve/ShortestPaths.py
mazelib/solve/Tremaux.pxd
mazelib/solve/Tremaux.py
mazelib/solve/__init__.py
mazelib/transmute/CuldeSacFiller.pxd
mazelib/transmute/CuldeSacFiller.py
mazelib/transmute/DeadEndFiller.pxd
mazelib/transmute/DeadEndFiller.py
mazelib/transmute/MazeTransmuteAlgo.pxd
mazelib/transmute/MazeTransmuteAlgo.py
mazelib/transmute/Perturbation.pxd
mazelib/transmute/Perturbation.py
mazelib/transmute/__init__.py
test/__init__.py
test/test_generators.py
test/test_maze.py
test/test_solvers.py
test/test_transmuters.py
mazelib_alt-0.9.14.dist-info/LICENSE
mazelib_alt-0.9.14.dist-info/METADATA
mazelib_alt-0.9.14.dist-info/WHEEL
mazelib_alt-0.9.14.dist-info/top_level.txt
mazelib_alt-0.9.14.dist-info/RECORD
